config.py
gentool.py
commands/__init__.py
commands/auth.py
commands/comfyui.py
commands/firebase_config.json
commands/workflows/sd15image.json
gentoolcli-0.1.4.dist-info/METADATA
gentoolcli-0.1.4.dist-info/WHEEL
gentoolcli-0.1.4.dist-info/entry_points.txt
gentoolcli-0.1.4.dist-info/top_level.txt
gentoolcli-0.1.4.dist-info/RECORD
