Metadata-Version: 2.4
Name: gentoolcli
Version: 0.1.4
Summary: CLI tool for Firebase and ComfyUI
Requires-Python: >=3.8
Requires-Dist: click
Requires-Dist: pyrebase4
Requires-Dist: setuptools
